finder/__init__.py
finder/__main__.py
finder/__pkg__.py
finder/api.py
finder/cli.py
finder/extensions.py
finder/schema.py
finder/utils.py
finder-1.0.2.dist-info/DESCRIPTION.rst
finder-1.0.2.dist-info/METADATA
finder-1.0.2.dist-info/RECORD
finder-1.0.2.dist-info/WHEEL
finder-1.0.2.dist-info/entry_points.txt
finder-1.0.2.dist-info/metadata.json
finder-1.0.2.dist-info/top_level.txt
