Metadata-Version: 1.1
Name: finder
Version: 1.0.2
Summary: Command line interface for searching a given pattern in the given directory/file paths
Home-page: https://github.com/bharadwajyarlagadda/finder
Author: Bharadwaj Yarlagadda
Author-email: yarlagaddabharadwaj@gmail.com
License: MIT License
Platform: UNKNOWN
Classifier: Development Status :: 3 - Alpha
Classifier: Intended Audience :: Developers
Classifier: Operating System :: OS Independent
Classifier: Programming Language :: Python
Classifier: License :: OSI Approved :: MIT License
Classifier: Topic :: Software Development :: Libraries
Classifier: Topic :: Software Development :: Libraries :: Python Modules
Classifier: Programming Language :: Python
Classifier: Programming Language :: Python :: 3
Classifier: Programming Language :: Python :: 3.3
Classifier: Programming Language :: Python :: 3.4
Classifier: Programming Language :: Python :: 3.5
